{"legislative_session": "2026", "identifier": "HB1453", "title": "relative to student school board members.", "from_organization": "~{\"classification\": \"lower\"}", "classification": ["bill"], "subject": [], "abstracts": [], "other_titles": [], "other_identifiers": [], "actions": [{"description": "Introduced 01/07/2026 and referred to Education Policy and Administration", "date": "2025-12-04", "organization_id": "~{\"classification\": \"lower\"}", "classification": ["introduction", "referral-committee"], "related_entities": []}], "sponsorships": [{"name": "Daniel E. Innis", "classification": "cosponsor", "entity_type": "person", "primary": false, "person_id": "~{\"name\": \"Daniel E. Innis\"}", "organization_id": null}, {"name": "Juliet Harvey-Bolia", "classification": "cosponsor", "entity_type": "person", "primary": false, "person_id": "~{\"name\": \"Juliet Harvey-Bolia\"}", "organization_id": null}, {"name": "Melissa A. Litchfield", "classification": "cosponsor", "entity_type": "person", "primary": false, "person_id": "~{\"name\": \"Melissa A. Litchfield\"}", "organization_id": null}, {"name": "Howard Pearl", "classification": "cosponsor", "entity_type": "person", "primary": false, "person_id": "~{\"name\": \"Howard Pearl\"}", "organization_id": null}, {"name": "Jonah Orion Wheeler", "classification": "cosponsor", "entity_type": "person", "primary": false, "person_id": "~{\"name\": \"Jonah Orion Wheeler\"}", "organization_id": null}, {"name": "James R Thibault", "classification": "primary", "entity_type": "person", "primary": true, "person_id": "~{\"name\": \"James R Thibault\"}", "organization_id": null}], "related_bills": [], "versions": [{"note": "latest version", "links": [{"url": "https://gc.nh.gov/lsr_search/billText.aspx?id=2082&type=4", "media_type": "text/html"}], "date": "", "classification": ""}], "documents": [], "citations": [], "sources": [{"url": "https://gc.nh.gov/bill_Status/billinfo.aspx?id=2082&inflect=2", "note": ""}], "extras": {"LSR": "2872", "_code": "3112"}, "jurisdiction": {"id": "ocd-jurisdiction/country:us/state:nh/government", "name": "New Hampshire", "classification": "state", "division_id": "ocd-division/country:us/state:nh"}, "scraped_at": "2026-01-30T08:30:56+00:00", "_id": "fe4aaf34-fdb5-11f0-88c5-ce85b53a38e0"}