{"legislative_session": "2026", "identifier": "HB1076", "title": "relative to authorizing or rescinding the use of electronic ballot counting devices.", "from_organization": "~{\"classification\": \"lower\"}", "classification": ["bill"], "subject": [], "abstracts": [], "other_titles": [], "other_identifiers": [], "actions": [{"description": "Introduced 01/07/2026 and referred to Municipal and County Government  HJ 1", "date": "2025-11-12", "organization_id": "~{\"classification\": \"lower\"}", "classification": ["introduction", "referral-committee"], "related_entities": []}, {"description": "Public Hearing: 01/30/2026 11:45 am GP 154", "date": "2026-01-21", "organization_id": "~{\"classification\": \"lower\"}", "classification": [], "related_entities": []}], "sponsorships": [{"name": "Diane Pauer", "classification": "cosponsor", "entity_type": "person", "primary": false, "person_id": "~{\"name\": \"Diane Pauer\"}", "organization_id": null}, {"name": "JD Bernardy", "classification": "cosponsor", "entity_type": "person", "primary": false, "person_id": "~{\"name\": \"JD Bernardy\"}", "organization_id": null}, {"name": "Glenn Bailey", "classification": "cosponsor", "entity_type": "person", "primary": false, "person_id": "~{\"name\": \"Glenn Bailey\"}", "organization_id": null}, {"name": "Mike S Belcher", "classification": "cosponsor", "entity_type": "person", "primary": false, "person_id": "~{\"name\": \"Mike S Belcher\"}", "organization_id": null}, {"name": "Claudine R Burnham", "classification": "cosponsor", "entity_type": "person", "primary": false, "person_id": "~{\"name\": \"Claudine R Burnham\"}", "organization_id": null}, {"name": "Kelley L Potenza", "classification": "cosponsor", "entity_type": "person", "primary": false, "person_id": "~{\"name\": \"Kelley L Potenza\"}", "organization_id": null}, {"name": "Susan G DeRoy", "classification": "primary", "entity_type": "person", "primary": true, "person_id": "~{\"name\": \"Susan G DeRoy\"}", "organization_id": null}, {"name": "Samuel G Farrington", "classification": "cosponsor", "entity_type": "person", "primary": false, "person_id": "~{\"name\": \"Samuel G Farrington\"}", "organization_id": null}], "related_bills": [], "versions": [{"note": "latest version", "links": [{"url": "https://gc.nh.gov/lsr_search/billText.aspx?id=1646&type=4", "media_type": "text/html"}], "date": "", "classification": ""}], "documents": [], "citations": [], "sources": [{"url": "https://gc.nh.gov/bill_Status/billinfo.aspx?id=1646&inflect=2", "note": ""}], "extras": {"LSR": "2444", "_code": "3115"}, "jurisdiction": {"id": "ocd-jurisdiction/country:us/state:nh/government", "name": "New Hampshire", "classification": "state", "division_id": "ocd-division/country:us/state:nh"}, "scraped_at": "2026-02-02T08:36:25+00:00", "_id": "42360f8c-0012-11f1-8637-0e2ad904228c"}