{"legislative_session": "2026", "identifier": "HB1114", "title": "relative to the documentation and preservation of public comment reports by standing legislative committees.", "from_organization": "~{\"classification\": \"lower\"}", "classification": ["bill"], "subject": [], "abstracts": [], "other_titles": [], "other_identifiers": [], "actions": [{"description": "Introduced 01/07/2026 and referred to Legislative Administration", "date": "2025-12-01", "organization_id": "~{\"classification\": \"lower\"}", "classification": ["introduction", "referral-committee"], "related_entities": []}, {"description": "Public Hearing: 01/22/2026 10:15 am GP 234", "date": "2026-01-08", "organization_id": "~{\"classification\": \"lower\"}", "classification": [], "related_entities": []}, {"description": "Executive Session: 01/29/2026 10:00 am GP 234", "date": "2026-01-22", "organization_id": "~{\"classification\": \"lower\"}", "classification": [], "related_entities": []}, {"description": "Majority Committee Report: Inexpedient to Legislate  01/29/2026 (Vote 8-3; RC)", "date": "2026-02-02", "organization_id": "~{\"classification\": \"lower\"}", "classification": ["committee-failure"], "related_entities": []}, {"description": "Minority Committee Report: Refer for Interim Study", "date": "2026-02-02", "organization_id": "~{\"classification\": \"lower\"}", "classification": [], "related_entities": []}], "sponsorships": [{"name": "Linda C Harriott-Gathright", "classification": "cosponsor", "entity_type": "person", "primary": false, "person_id": "~{\"name\": \"Linda C Harriott-Gathright\"}", "organization_id": null}, {"name": "Rebecca Perkins Kwoka", "classification": "cosponsor", "entity_type": "person", "primary": false, "person_id": "~{\"name\": \"Rebecca Perkins Kwoka\"}", "organization_id": null}, {"name": "Mary A Hakken-Phillips", "classification": "cosponsor", "entity_type": "person", "primary": false, "person_id": "~{\"name\": \"Mary A Hakken-Phillips\"}", "organization_id": null}, {"name": "Heather Raymond", "classification": "cosponsor", "entity_type": "person", "primary": false, "person_id": "~{\"name\": \"Heather Raymond\"}", "organization_id": null}, {"name": "Peggy Balboni", "classification": "cosponsor", "entity_type": "person", "primary": false, "person_id": "~{\"name\": \"Peggy Balboni\"}", "organization_id": null}, {"name": "Hope E Damon", "classification": "cosponsor", "entity_type": "person", "primary": false, "person_id": "~{\"name\": \"Hope E Damon\"}", "organization_id": null}, {"name": "Paige Beauchemin", "classification": "cosponsor", "entity_type": "person", "primary": false, "person_id": "~{\"name\": \"Paige Beauchemin\"}", "organization_id": null}, {"name": "Terri O'Rorke", "classification": "cosponsor", "entity_type": "person", "primary": false, "person_id": "~{\"name\": \"Terri O'Rorke\"}", "organization_id": null}, {"name": "Janet Marie Lucas", "classification": "primary", "entity_type": "person", "primary": true, "person_id": "~{\"name\": \"Janet Marie Lucas\"}", "organization_id": null}, {"name": "Thomas Oppel", "classification": "cosponsor", "entity_type": "person", "primary": false, "person_id": "~{\"name\": \"Thomas Oppel\"}", "organization_id": null}, {"name": "Alice Wade", "classification": "cosponsor", "entity_type": "person", "primary": false, "person_id": "~{\"name\": \"Alice Wade\"}", "organization_id": null}], "related_bills": [], "versions": [{"note": "latest version", "links": [{"url": "https://gc.nh.gov/lsr_search/billText.aspx?id=1770&type=4", "media_type": "text/html"}], "date": "", "classification": ""}], "documents": [], "citations": [], "sources": [{"url": "https://gc.nh.gov/bill_Status/billinfo.aspx?id=1770&inflect=2", "note": ""}], "extras": {"LSR": "2565", "_code": "4017"}, "jurisdiction": {"id": "ocd-jurisdiction/country:us/state:nh/government", "name": "New Hampshire", "classification": "state", "division_id": "ocd-division/country:us/state:nh"}, "scraped_at": "2026-02-04T08:34:09+00:00", "_id": "457b3bde-01a4-11f1-9a7f-1aeb09d5f5e0"}