{"legislative_session": "2026", "identifier": "HB1056", "title": "establishing a commission to study the impacts of reinsurance on the cost and availability of property insurance in New Hampshire.", "from_organization": "~{\"classification\": \"lower\"}", "classification": ["bill"], "subject": [], "abstracts": [], "other_titles": [], "other_identifiers": [], "actions": [{"description": "Introduced 01/07/2026 and referred to Commerce and Consumer Affairs  HJ 1", "date": "2025-11-07", "organization_id": "~{\"classification\": \"lower\"}", "classification": ["introduction", "referral-committee"], "related_entities": []}, {"description": "Public Hearing: 02/04/2026 11:15 am GP 229", "date": "2026-01-29", "organization_id": "~{\"classification\": \"lower\"}", "classification": [], "related_entities": []}], "sponsorships": [{"name": "John R Cloutier", "classification": "cosponsor", "entity_type": "person", "primary": false, "person_id": "~{\"name\": \"John R Cloutier\"}", "organization_id": null}, {"name": "Karen E Ebel", "classification": "cosponsor", "entity_type": "person", "primary": false, "person_id": "~{\"name\": \"Karen E Ebel\"}", "organization_id": null}, {"name": "Suzanne M. Vail", "classification": "cosponsor", "entity_type": "person", "primary": false, "person_id": "~{\"name\": \"Suzanne M. Vail\"}", "organization_id": null}, {"name": "Anita D Burroughs", "classification": "cosponsor", "entity_type": "person", "primary": false, "person_id": "~{\"name\": \"Anita D Burroughs\"}", "organization_id": null}, {"name": "Tony M Caplan", "classification": "cosponsor", "entity_type": "person", "primary": false, "person_id": "~{\"name\": \"Tony M Caplan\"}", "organization_id": null}, {"name": "Heath Howard", "classification": "cosponsor", "entity_type": "person", "primary": false, "person_id": "~{\"name\": \"Heath Howard\"}", "organization_id": null}, {"name": "Carry Spier", "classification": "primary", "entity_type": "person", "primary": true, "person_id": "~{\"name\": \"Carry Spier\"}", "organization_id": null}, {"name": "Linda J Haskins", "classification": "cosponsor", "entity_type": "person", "primary": false, "person_id": "~{\"name\": \"Linda J Haskins\"}", "organization_id": null}], "related_bills": [], "versions": [{"note": "latest version", "links": [{"url": "https://gc.nh.gov/lsr_search/billText.aspx?id=1775&type=4", "media_type": "text/html"}], "date": "", "classification": ""}], "documents": [], "citations": [], "sources": [{"url": "https://gc.nh.gov/bill_Status/billinfo.aspx?id=1775&inflect=2", "note": ""}], "extras": {"LSR": "2570", "_code": "4026"}, "jurisdiction": {"id": "ocd-jurisdiction/country:us/state:nh/government", "name": "New Hampshire", "classification": "state", "division_id": "ocd-division/country:us/state:nh"}, "scraped_at": "2026-02-03T08:30:21+00:00", "_id": "92f81686-00da-11f1-8a0c-f24666aa0fff"}